freemindlatex/__entry__.py
freemindlatex/__init__.py
freemindlatex/__main__.py
freemindlatex/compilation_client_lib.py
freemindlatex/compilation_server_lib.py
freemindlatex/compilation_service_pb2.py
freemindlatex/convert.py
freemindlatex/run_app.py
freemindlatex-1.0.2.data/data/share/freemindlatex/example/mindmap.mm
freemindlatex-1.0.2.data/data/share/freemindlatex/freemind/FreeMind.exe
freemindlatex-1.0.2.data/data/share/freemindlatex/freemind/FreeMind64.exe
freemindlatex-1.0.2.data/data/share/freemindlatex/freemind/dictionaries.properties
freemindlatex-1.0.2.data/data/share/freemindlatex/freemind/dictionary_de.ortho
freemindlatex-1.0.2.data/data/share/freemindlatex/freemind/dictionary_en.ortho
freemindlatex-1.0.2.data/data/share/freemindlatex/freemind/dictionary_es.ortho
freemindlatex-1.0.2.data/data/share/freemindlatex/freemind/dictionary_fr.ortho
freemindlatex-1.0.2.data/data/share/freemindlatex/freemind/dictionary_nl.ortho
freemindlatex-1.0.2.data/data/share/freemindlatex/freemind/dictionary_ru.ortho
freemindlatex-1.0.2.data/data/share/freemindlatex/freemind/freemind.bat
freemindlatex-1.0.2.data/data/share/freemindlatex/freemind/freemind.sh
freemindlatex-1.0.2.data/data/share/freemindlatex/freemind/freemindw.bat
freemindlatex-1.0.2.data/data/share/freemindlatex/freemind/license
freemindlatex-1.0.2.data/data/share/freemindlatex/freemind/patterns.xml
freemindlatex-1.0.2.data/data/share/freemindlatex/freemind/accessories/ExportToHtml.groovy
freemindlatex-1.0.2.data/data/share/freemindlatex/freemind/accessories/ExportToPdf.groovy
freemindlatex-1.0.2.data/data/share/freemindlatex/freemind/accessories/LICENSE.MIT
freemindlatex-1.0.2.data/data/share/freemindlatex/freemind/accessories/freemind2applet.xsl
freemindlatex-1.0.2.data/data/share/freemindlatex/freemind/accessories/freemind2flash.xsl
freemindlatex-1.0.2.data/data/share/freemindlatex/freemind/accessories/freemind2html.css
freemindlatex-1.0.2.dist-info/DESCRIPTION.rst
freemindlatex-1.0.2.dist-info/METADATA
freemindlatex-1.0.2.dist-info/RECORD
freemindlatex-1.0.2.dist-info/WHEEL
freemindlatex-1.0.2.dist-info/entry_points.txt
freemindlatex-1.0.2.dist-info/metadata.json
freemindlatex-1.0.2.dist-info/top_level.txt
freemindlatex-1.0.2.dist-info/zip-safe
