Metadata-Version: 2.0
Name: freemindlatex
Version: 1.0.2
Summary: Compiles your freemind document into latex beamer.
Home-page: https://github.com/xuehuichao/freemind-latex
Author: Huichao Xue
Author-email: xue.huichao@gmail.com
License: GPLv2
Keywords: freemind beamer latex slides editor
Platform: any
Requires-Dist: bibtexparser
Requires-Dist: futures
Requires-Dist: gevent
Requires-Dist: google-apputils
Requires-Dist: grpcio
Requires-Dist: portpicker
Requires-Dist: protobuf
Requires-Dist: pypdf2
Requires-Dist: python-gflags
Requires-Dist: six
Requires-Dist: timeout-decorator
